[
{
 "name": "BLEU",
 "score": 10.8,
 "signature": "nrefs:1|case:mixed|eff:no|tok:spm-flores|smooth:none|version:2.1.0",
 "verbose_score": "39.0/17.7/9.3/5.0 (BP = 0.807 ratio = 0.824 hyp_len = 32916 ref_len = 39960)",
 "nrefs": "1",
 "case": "mixed",
 "eff": "no",
 "tok": "spm-flores",
 "smooth": "none",
 "version": "2.1.0"
},
{
 "name": "chrF2",
 "score": 28.0,
 "signature": "nrefs:1|case:mixed|eff:yes|nc:6|nw:0|space:no|version:2.1.0",
 "nrefs": "1",
 "case": "mixed",
 "eff": "yes",
 "nc": "6",
 "nw": "0",
 "space": "no",
 "version": "2.1.0"
}
]
