[
{
 "name": "BLEU",
 "score": 36.9,
 "signature": "nrefs:1|case:mixed|eff:no|tok:spm-flores|smooth:none|version:2.1.0",
 "verbose_score": "59.6/43.2/32.8/25.0 (BP = 0.968 ratio = 0.969 hyp_len = 46188 ref_len = 47684)",
 "nrefs": "1",
 "case": "mixed",
 "eff": "no",
 "tok": "spm-flores",
 "smooth": "none",
 "version": "2.1.0"
},
{
 "name": "chrF2",
 "score": 49.0,
 "signature": "nrefs:1|case:mixed|eff:yes|nc:6|nw:0|space:no|version:2.1.0",
 "nrefs": "1",
 "case": "mixed",
 "eff": "yes",
 "nc": "6",
 "nw": "0",
 "space": "no",
 "version": "2.1.0"
}
]
